cloudtruth_mcp/__init__.py
cloudtruth_mcp/cache.py
cloudtruth_mcp/client.py
cloudtruth_mcp/config.py
cloudtruth_mcp/errors.py
cloudtruth_mcp/models.py
cloudtruth_mcp/prompts.py
cloudtruth_mcp/resources.py
cloudtruth_mcp/server.py
cloudtruth_mcp/tools.py
cloudtruth_mcp/utils.py
cloudtruth_mcp_server-1.0.3.dist-info/licenses/LICENSE
cloudtruth_mcp_server-1.0.3.dist-info/METADATA
cloudtruth_mcp_server-1.0.3.dist-info/WHEEL
cloudtruth_mcp_server-1.0.3.dist-info/entry_points.txt
cloudtruth_mcp_server-1.0.3.dist-info/top_level.txt
cloudtruth_mcp_server-1.0.3.dist-info/RECORD
