Metadata-Version: 2.4
Name: cloudtruth-mcp-server
Version: 1.0.3
Summary: MCP server for CloudTruth configuration and secrets management
Author-email: CloudTruth <support@cloudtruth.com>
License: MIT
Requires-Python: >=3.11
License-File: LICENSE
Requires-Dist: mcp>=1.0.0
Requires-Dist: httpx>=0.25.0
Requires-Dist: pydantic>=2.0.0
Provides-Extra: dev
Requires-Dist: pytest>=7.0.0; extra == "dev"
Requires-Dist: pytest-asyncio>=0.21.0; extra == "dev"
Requires-Dist: pytest-cov>=4.0.0; extra == "dev"
Requires-Dist: black>=23.0.0; extra == "dev"
Requires-Dist: ruff>=0.1.0; extra == "dev"
Requires-Dist: mypy>=1.0.0; extra == "dev"
Dynamic: license-file
